README.md
setup.py
pyfluence/__init__.py
pyfluence/confluence.py
pyfluence.egg-info/PKG-INFO
pyfluence.egg-info/SOURCES.txt
pyfluence.egg-info/dependency_links.txt
pyfluence.egg-info/entry_points.txt
pyfluence.egg-info/requires.txt
pyfluence.egg-info/top_level.txt
pyfluence/tests/__init__.py
pyfluence/tests/test_confluence.py