Metadata-Version: 2.1
Name: pyfluence
Version: 0.2.1
Summary: Confluence REST API client for Python
Home-page: https://github.com/kshehadeh/pyfluence
Author: Karim Shehadeh
Author-email: karim@karim.cloud
License: MIT
Keywords: confluence development rest api atlassian
Platform: UNKNOWN
Classifier: Development Status :: 3 - Alpha
Classifier: Intended Audience :: Developers
Classifier: License :: OSI Approved :: MIT License
Classifier: Programming Language :: Python :: 3.6
Provides-Extra: dev
Provides-Extra: test
